logify/__init__.py
logify-0.0.2.dist-info/LICENSE
logify-0.0.2.dist-info/METADATA
logify-0.0.2.dist-info/WHEEL
logify-0.0.2.dist-info/top_level.txt
logify-0.0.2.dist-info/RECORD
