Metadata-Version: 2.1
Name: logify
Version: 0.0.2
Summary: Python package for script logging and DataDog integration
Home-page: https://github.com/tsoisauce/logify
Author: Kelvin Tsoi
Author-email: kelvin@hellospork.com
License: UNKNOWN
Platform: UNKNOWN
Classifier: Programming Language :: Python :: 3
Classifier: License :: OSI Approved :: MIT License
Classifier: Operating System :: OS Independent
Requires-Python: >=3.7
Requires-Dist: termcolor
